{
  "$schema": "https://ui.shadcn.com/schema/registry-item.json",
  "name": "icon-brain",
  "type": "registry:component",
  "title": "Animated Brain",
  "description": "Brain with neural pulse and connection glow.",
  "dependencies": [
    "motion"
  ],
  "files": [
    {
      "path": "registry/default/icon-brain/icon-brain.tsx",
      "content": "\"use client\";\r\n\r\nimport { motion, useReducedMotion, type Variants } from \"framer-motion\";\r\n\r\nexport interface IconBrainProps extends React.SVGProps<SVGSVGElement> {\r\n  size?: number;\r\n  strokeWidth?: number;\r\n}\r\n\r\nconst leftBrainVariants: Variants = {\r\n  rest: { opacity: 1 },\r\n  hover: {\r\n    opacity: [1, 0.7, 1],\r\n    transition: {\r\n      duration: 2,\r\n      repeat: Infinity,\r\n      ease: \"easeInOut\",\r\n    },\r\n  },\r\n};\r\n\r\nconst rightBrainVariants: Variants = {\r\n  rest: { opacity: 1 },\r\n  hover: {\r\n    opacity: [1, 0.7, 1],\r\n    transition: {\r\n      duration: 2,\r\n      repeat: Infinity,\r\n      delay: 1,\r\n      ease: \"easeInOut\",\r\n    },\r\n  },\r\n};\r\n\r\nconst pulseVariants: Variants = {\r\n  rest: { scale: 1 },\r\n  hover: {\r\n    scale: [1, 1.05, 1],\r\n    transition: {\r\n      duration: 2,\r\n      repeat: Infinity,\r\n      ease: \"easeInOut\",\r\n    },\r\n  },\r\n};\r\n\r\nexport function IconBrain({\r\n  size = 24,\r\n  strokeWidth = 2,\r\n  className,\r\n  ...props\r\n}: IconBrainProps) {\r\n  const { onAnimationStart, onAnimationEnd, onDragStart, onDrag, onDragEnd, ...restOptions } = props;\r\n  const prefersReducedMotion = useReducedMotion();\r\n\r\n  return (\r\n    <motion.svg\r\n      xmlns=\"http://www.w3.org/2000/svg\"\r\n      width={size}\r\n      height={size}\r\n      viewBox=\"0 0 24 24\"\r\n      fill=\"none\"\r\n      stroke=\"currentColor\"\r\n      strokeWidth={strokeWidth}\r\n      strokeLinecap=\"round\"\r\n      strokeLinejoin=\"round\"\r\n      initial={prefersReducedMotion ? false : \"rest\"}\r\n      whileHover={prefersReducedMotion ? undefined : \"hover\"}\r\n      whileTap={prefersReducedMotion ? undefined : \"tap\"}\r\n      className={`outline-none focus:outline-none focus:ring-0 select-none ${className ?? \"\"}`.trim()}\r\n      style={{ overflow: \"visible\" }}\r\n      {...restOptions}\r\n    >\r\n      <motion.g variants={pulseVariants}>\r\n        <motion.path \r\n          d=\"M12 4.5a2.5 2.5 0 0 0-4.96-.46 2.5 2.5 0 0 0-1.98 3 2.5 2.5 0 0 0-1.32 4 2.5 2.5 0 0 0 .15 4.5 2.5 2.5 0 0 0 4.14 2 2.5 2.5 0 0 0 4.46-1.54V5a2.5 2.5 0 0 0-.49-.5Z\" \r\n          variants={leftBrainVariants}\r\n        />\r\n        <motion.path \r\n          d=\"M12 4.5a2.5 2.5 0 0 1 4.96-.46 2.5 2.5 0 0 1 1.98 3 2.5 2.5 0 0 1 1.32 4 2.5 2.5 0 0 1-.15 4.5 2.5 2.5 0 0 1-4.14 2 2.5 2.5 0 0 1-4.46-1.54V5c0-.17.017-.333.05-.5Z\" \r\n          variants={rightBrainVariants}\r\n        />\r\n      </motion.g>\r\n    </motion.svg>\r\n  );\r\n}\r\n",
      "type": "registry:component"
    }
  ]
}