{
  "$schema": "https://ui.shadcn.com/schema/registry-item.json",
  "name": "icon-at-sign",
  "type": "registry:component",
  "title": "Animated At Sign",
  "description": "At-sign with spiral drawing and pulse animation.",
  "dependencies": [
    "motion"
  ],
  "files": [
    {
      "path": "registry/default/icon-at-sign/icon-at-sign.tsx",
      "content": "\"use client\";\r\n\r\nimport { motion, useReducedMotion, type Variants } from \"framer-motion\";\r\n\r\nexport interface IconAtSignProps extends React.SVGProps<SVGSVGElement> {\r\n  size?: number;\r\n  strokeWidth?: number;\r\n}\r\n\r\nconst spiralVariants: Variants = {\r\n  rest: { pathLength: 1, opacity: 1 },\r\n  hover: {\r\n    pathLength: [1, 0, 1],\r\n    opacity: [1, 0.6, 1],\r\n    transition: {\r\n      duration: 2,\r\n      repeat: Infinity,\r\n      ease: \"easeInOut\",\r\n    },\r\n  },\r\n};\r\n\r\nconst circleVariants: Variants = {\r\n  rest: { scale: 1 },\r\n  hover: {\r\n    scale: [1, 1.2, 1],\r\n    transition: {\r\n      duration: 1.5,\r\n      repeat: Infinity,\r\n      ease: \"easeInOut\",\r\n    },\r\n  },\r\n};\r\n\r\nexport function IconAtSign({\r\n  size = 24,\r\n  strokeWidth = 2,\r\n  className,\r\n  ...props\r\n}: IconAtSignProps) {\r\n  const { onAnimationStart, onAnimationEnd, onDragStart, onDrag, onDragEnd, ...restOptions } = props;\r\n  const prefersReducedMotion = useReducedMotion();\r\n\r\n  return (\r\n    <motion.svg\r\n      xmlns=\"http://www.w3.org/2000/svg\"\r\n      width={size}\r\n      height={size}\r\n      viewBox=\"0 0 24 24\"\r\n      fill=\"none\"\r\n      stroke=\"currentColor\"\r\n      strokeWidth={strokeWidth}\r\n      strokeLinecap=\"round\"\r\n      strokeLinejoin=\"round\"\r\n      initial={prefersReducedMotion ? false : \"rest\"}\r\n      whileHover={prefersReducedMotion ? undefined : \"hover\"}\r\n      whileTap={prefersReducedMotion ? undefined : \"tap\"}\r\n      className={`outline-none focus:outline-none focus:ring-0 select-none ${className ?? \"\"}`.trim()}\r\n      style={{ overflow: \"visible\" }}\r\n      {...restOptions}\r\n    >\r\n      <motion.circle cx=\"12\" cy=\"12\" r=\"4\" style={{ originX: \"12px\", originY: \"12px\" }} variants={prefersReducedMotion ? {} : circleVariants} />\r\n      <motion.path d=\"M16 8v5a3 3 0 0 0 6 0v-1a10 10 0 1 0-4 8\" variants={spiralVariants} />\r\n    </motion.svg>\r\n  );\r\n}\r\n",
      "type": "registry:component"
    }
  ]
}