{
  "$schema": "https://ui.shadcn.com/schema/registry-item.json",
  "name": "icon-scan",
  "type": "registry:component",
  "title": "Animated Scan",
  "description": "Scan with corner pulse and horizontal line flicker.",
  "dependencies": [
    "motion"
  ],
  "files": [
    {
      "path": "registry/default/icon-scan/icon-scan.tsx",
      "content": "\"use client\";\r\n\r\nimport { motion, useReducedMotion, type Variants } from \"framer-motion\";\r\n\r\nexport interface IconScanProps extends React.SVGProps<SVGSVGElement> {\r\n  size?: number;\r\n  strokeWidth?: number;\r\n}\r\n\r\nconst cornerVariants: Variants = {\r\n  rest: { scale: 1, opacity: 1 },\r\n  hover: {\r\n    scale: [1, 1.05, 1],\r\n    opacity: [1, 0.7, 1],\r\n    transition: {\r\n      duration: 1.5,\r\n      repeat: Infinity,\r\n      ease: \"easeInOut\",\r\n    },\r\n  },\r\n};\r\n\r\nconst scanLineVariants: Variants = {\r\n  rest: { y: 0, opacity: 0 },\r\n  hover: {\r\n    y: [7, 17, 7],\r\n    opacity: [0, 1, 0.5, 1, 0],\r\n    transition: {\r\n      duration: 2,\r\n      repeat: Infinity,\r\n      ease: \"linear\",\r\n    },\r\n  },\r\n};\r\n\r\nexport function IconScan({\r\n  size = 24,\r\n  strokeWidth = 2,\r\n  className,\r\n  ...props\r\n}: IconScanProps) {\r\n  const { onAnimationStart, onAnimationEnd, onDragStart, onDrag, onDragEnd, ...restOptions } = props;\r\n  const prefersReducedMotion = useReducedMotion();\r\n\r\n  return (\r\n    <motion.svg\r\n      xmlns=\"http://www.w3.org/2000/svg\"\r\n      width={size}\r\n      height={size}\r\n      viewBox=\"0 0 24 24\"\r\n      fill=\"none\"\r\n      stroke=\"currentColor\"\r\n      strokeWidth={strokeWidth}\r\n      strokeLinecap=\"round\"\r\n      strokeLinejoin=\"round\"\r\n      initial={prefersReducedMotion ? false : \"rest\"}\r\n      whileHover={prefersReducedMotion ? undefined : \"hover\"}\r\n      whileTap={prefersReducedMotion ? undefined : \"tap\"}\r\n      className={`outline-none focus:outline-none focus:ring-0 select-none ${className ?? \"\"}`.trim()}\r\n      style={{ overflow: \"visible\" }}\r\n      {...restOptions}\r\n    >\r\n      {/* Corner Brackets */}\r\n      <motion.path d=\"M3 7V5a2 2 0 0 1 2-2h2\" variants={cornerVariants} />\r\n      <motion.path d=\"M17 3h2a2 2 0 0 1 2 2v2\" variants={cornerVariants} />\r\n      <motion.path d=\"M21 17v2a2 2 0 0 1-2 2h-2\" variants={cornerVariants} />\r\n      <motion.path d=\"M7 21H5a2 2 0 0 1-2-2v-2\" variants={cornerVariants} />\r\n      \r\n      {/* Top-to-Bottom Scan Line */}\r\n      <motion.path \r\n        d=\"M7 0h10\" \r\n        variants={scanLineVariants}\r\n        strokeWidth={strokeWidth}\r\n        className=\"text-primary\"\r\n      />\r\n    </motion.svg>\r\n  );\r\n}\r\n",
      "type": "registry:component"
    }
  ]
}